pyjectify/__init__.py
pyjectify/windows/__init__.py
pyjectify/windows/core/defines.py
pyjectify/windows/core/pe.py
pyjectify/windows/core/process.py
pyjectify/windows/modules/hook.py
pyjectify/windows/modules/inject.py
pyjectify/windows/modules/memscan.py
pyjectify/windows/modules/pythonlib.py
pyjectify/windows/utils/apisetschema.py
pyjectify/windows/utils/syscall.py
pyjectify-1.0.dist-info/LICENSE
pyjectify-1.0.dist-info/METADATA
pyjectify-1.0.dist-info/WHEEL
pyjectify-1.0.dist-info/top_level.txt
pyjectify-1.0.dist-info/RECORD
