Metadata-Version: 2.2
Name: pyjectify
Version: 1.0
Summary: A Python library for memory manipulation, code injection and function hooking
Author: Petitoto
Project-URL: Homepage, https://github.com/Petitoto/pyjectify
Project-URL: Bug Tracker, https://github.com/Petitoto/pyjectify/issues
Classifier: Programming Language :: Python :: 3
Classifier: License :: OSI Approved :: MIT License
Classifier: Operating System :: OS Independent
Requires-Python: >=3.10
License-File: LICENSE
